{
  "$schema": "https://next.park-ui.com/schema/registry-item.json",
  "id": "code",
  "type": "component",
  "files": [
    {
      "type": "component",
      "fileName": "code.tsx",
      "content": "import { ark } from '@ark-ui/react/factory'\nimport type { ComponentProps } from 'react'\nimport { styled } from 'styled-system/jsx'\nimport { code } from 'styled-system/recipes'\n\nexport type CodeProps = ComponentProps<typeof Code>\nexport const Code = styled(ark.div, code)\n",
      "indexFile": {
        "exports": [
          {
            "type": "named",
            "symbols": [
              {
                "name": "Code",
                "isType": false
              },
              {
                "name": "CodeProps",
                "isType": true
              }
            ],
            "moduleSpecifier": "./code"
          }
        ]
      }
    },
    {
      "type": "recipe",
      "fileName": "code.ts",
      "content": "import { defineRecipe } from '@pandacss/dev'\n\nexport const code = defineRecipe({\n  className: 'code',\n  base: {\n    alignItems: 'center',\n    borderRadius: 'l2',\n    display: 'inline-flex',\n    fontVariantNumeric: 'tabular-nums',\n    fontWeight: 'medium',\n    fontFamily: 'code',\n    gap: '1',\n    whiteSpace: 'pre',\n  },\n  defaultVariants: {\n    size: 'md',\n    variant: 'subtle',\n  },\n  variants: {\n    variant: {\n      solid: {\n        bg: 'colorPalette.solid',\n        color: 'colorPalette.contrast',\n      },\n      surface: {\n        background: 'colorPalette.a2',\n        color: 'colorPalette.a11',\n        shadow: 'inset 0 0 0px 1px var(--shadow-color)',\n        shadowColor: 'colorPalette.a7',\n      },\n      subtle: {\n        background: 'colorPalette.a3',\n        color: 'colorPalette.a11',\n      },\n      outline: {\n        color: 'colorPalette.a11',\n        shadow: 'inset 0 0 0px 1px var(--shadow-color)',\n        shadowColor: 'colorPalette.a8',\n      },\n      plain: {\n        color: 'colorPalette.a11',\n      },\n    },\n    size: {\n      sm: {\n        minHeight: '5',\n        px: '0.5',\n        textStyle: 'xs',\n      },\n      md: {\n        minHeight: '6',\n        textStyle: 'sm',\n        px: '1',\n        py: '1px',\n      },\n      lg: {\n        minHeight: '7',\n        px: '1.5',\n        py: '1px',\n        textStyle: 'md',\n      },\n    },\n  },\n})\n",
      "indexFile": {
        "imports": [
          {
            "type": "named",
            "moduleSpecifier": "./code",
            "symbols": [
              {
                "name": "code"
              }
            ]
          }
        ],
        "exports": [
          {
            "type": "object-literal",
            "variableName": "recipes",
            "properties": [
              {
                "name": "code"
              }
            ]
          }
        ]
      }
    }
  ]
}