{
  "$schema": "https://park-ui.com/schema/registry-item.json",
  "name": "group-recipe",
  "type": "registry:recipe",
  "dependencies": ["@pandacss/dev"],
  "files": [
    {
      "content": "import { defineRecipe } from '@pandacss/dev'\n\nexport const group = defineRecipe({\n  className: 'group',\n  base: {\n    display: 'inline-flex',\n    position: 'relative',\n    gap: '2',\n    '& > *': {\n      _focusVisible: {\n        zIndex: 1,\n      },\n    },\n  },\n  defaultVariants: {\n    orientation: 'horizontal',\n  },\n  variants: {\n    orientation: {\n      horizontal: {\n        flexDirection: 'row',\n      },\n      vertical: {\n        flexDirection: 'column',\n      },\n    },\n    attached: {\n      true: {\n        gap: '0',\n      },\n    },\n    grow: {\n      true: {\n        display: 'flex',\n        '& > *': {\n          flex: 1,\n        },\n      },\n    },\n  },\n  compoundVariants: [\n    {\n      orientation: 'horizontal',\n      attached: true,\n      css: {\n        '& > *:first-child': {\n          borderEndRadius: '0',\n          marginEnd: '-1px',\n        },\n        '& > *:last-child': {\n          borderStartRadius: '0',\n        },\n        '& > *:not(:first-child):not(:last-child)': {\n          borderRadius: '0',\n          marginEnd: '-1px',\n        },\n      },\n    },\n    {\n      orientation: 'vertical',\n      attached: true,\n      css: {\n        '& > *:first-child': {\n          borderBottomRadius: '0',\n          marginBottom: '-1px',\n        },\n        '& > *:last-child': {\n          borderTopRadius: '0',\n        },\n        '& > *:not(:first-child):not(:last-child)': {\n          borderRadius: '0',\n          marginBottom: '-1px',\n        },\n      },\n    },\n  ],\n})\n",
      "type": "registry:recipe",
      "path": "group.ts",
      "imports": "import { group } from './group'"
    }
  ]
}
